my_own_package/__init__.py
Elena_first_package-0.1.0.dist-info/METADATA
Elena_first_package-0.1.0.dist-info/WHEEL
Elena_first_package-0.1.0.dist-info/top_level.txt
Elena_first_package-0.1.0.dist-info/RECORD
