Metadata-Version: 2.1
Name: Elena-first-package
Version: 0.1.0
Summary: This is the first package by Elena
Home-page: UNKNOWN
Author: Elena Kruger
Author-email: elenaalinakruger@gmail.com
License: UNKNOWN
Platform: UNKNOWN
